config/__init__.py
config/local.py
config/settings.py
config/urls.py
config/wsgi.py
rest_pyotp/__init__.py
rest_pyotp/admin.py
rest_pyotp/apps.py
rest_pyotp/mixins.py
rest_pyotp/models.py
rest_pyotp/routers.py
rest_pyotp/serializers.py
rest_pyotp/tests.py
rest_pyotp/views.py
rest_pyotp/migrations/0001_initial.py
rest_pyotp/migrations/__init__.py
drf_pyotp-0.6.0.dist-info/LICENSE.txt
drf_pyotp-0.6.0.dist-info/METADATA
drf_pyotp-0.6.0.dist-info/WHEEL
drf_pyotp-0.6.0.dist-info/top_level.txt
drf_pyotp-0.6.0.dist-info/RECORD
